HISTORY.rst
LICENSE
MANIFEST.in
README.rst
ds4drv.conf
setup.py
ds4drv/__init__.py
ds4drv/__main__.py
ds4drv/actions.py
ds4drv/backend.py
ds4drv/config.py
ds4drv/daemon.py
ds4drv/device.py
ds4drv/eventloop.py
ds4drv/exceptions.py
ds4drv/logger.py
ds4drv/uinput.py
ds4drv/utils.py
ds4drv.egg-info/PKG-INFO
ds4drv.egg-info/SOURCES.txt
ds4drv.egg-info/dependency_links.txt
ds4drv.egg-info/entry_points.txt
ds4drv.egg-info/requires.txt
ds4drv.egg-info/top_level.txt
ds4drv/backends/__init__.py
ds4drv/backends/bluetooth.py
ds4drv/backends/hidraw.py
ds4drv/packages/__init__.py
ds4drv/packages/timerfd.py
systemd/ds4drv.service