Metadata-Version: 1.1
Name: ds4drv
Version: 0.5.0
Summary: A Sony DualShock 4 userspace driver for Linux
Home-page: https://github.com/chrippa/ds4drv
Author: Christopher Rosell
Author-email: chrippa@tanuki.se
License: MIT
Platform: UNKNOWN
Classifier: Development Status :: 4 - Beta
Classifier: Environment :: Console
Classifier: License :: OSI Approved :: MIT License
Classifier: Operating System :: POSIX :: Linux
Classifier: Programming Language :: Python :: 2.7
Classifier: Programming Language :: Python :: 3.3
Classifier: Topic :: Games/Entertainment
